<ac:structured-macro ac:name="info">
 <ac:rich-text-body>
<ac:structured-macro ac:name="expand">
  <ac:parameter ac:name="title">Click here for content instructions...</ac:parameter>
  <ac:rich-text-body>
      <h4>Contents</h4>
      <p>A list of identified technical risks, ordered by priority</p>
      
      <h4>Motivation</h4>
      <p>“Risk management is project management for grown-ups” (Tim Lister, Atlantic Systems Guild.) This should be your motto for systematic detection and evaluation of technical risks in the architecture, which will be needed by project management as part of the overall risk analysis.</p>
      
      <h4>Form</h4>
      <p>List of risks with probability of occurrence, amount of damage, options for risk avoidance or risk mitigation, …</p>
  </ac:rich-text-body>
    </ac:structured-macro>
  </ac:rich-text-body>
</ac:structured-macro>